CONTRIBUTING.md
LICENSE
MANIFEST.in
Makefile
README.md
pyproject.toml
setup.cfg
setup.py
SpotifyPictureHelper/__init__.py
SpotifyPictureHelper/_version.py
SpotifyPictureHelper/main.py
SpotifyPictureHelper.egg-info/PKG-INFO
SpotifyPictureHelper.egg-info/SOURCES.txt
SpotifyPictureHelper.egg-info/dependency_links.txt
SpotifyPictureHelper.egg-info/entry_points.txt
SpotifyPictureHelper.egg-info/not-zip-safe
SpotifyPictureHelper.egg-info/requires.txt
SpotifyPictureHelper.egg-info/top_level.txt
SpotifyPictureHelper/tests/blackWhite.png
SpotifyPictureHelper/tests/fakeArtist.html
SpotifyPictureHelper/tests/fakePlaylist.html
SpotifyPictureHelper/tests/fakeUser.html
SpotifyPictureHelper/tests/overlay.png
SpotifyPictureHelper/tests/test2.png
SpotifyPictureHelper/tests/test_all.py