Metadata-Version: 2.1
Name: SpotifyPictureHelper
Version: 0.2.1
Summary: A python library that helps with the analysis of Spotify pictures.
Home-page: UNKNOWN
Author: Daisy ye
Author-email: daisyye20010730@gmail.com
License: UNKNOWN
Platform: UNKNOWN
Requires-Python: >=3.7
Provides-Extra: pdf
Provides-Extra: rest
